{
  "priority": 50,
  "style": "clarity_tooltips:blue",
  "filter": {
    "type": "obscure_tooltips:item",
    "values": [
      "blue_banner",
      "blue_bed",
      "blue_bundle",
      "blue_candle",
      "blue_carpet",
      "blue_concrete",
      "blue_concrete_powder",
      "blue_dye",
      "blue_glazed_terracotta",
      "blue_harness",
      "blue_shulker_box",
      "blue_stained_glass",
      "blue_stained_glass_pane",
      "blue_terracotta",
      "blue_wool",
      "aether:blue_cape",
      "another_furniture:blue_curtain",
      "another_furniture:blue_lamp",
      "another_furniture:blue_sofa",
      "another_furniture:blue_stool",
      "another_furniture:blue_tall_stool",
      "comforts:hammock_blue",
      "comforts:sleeping_bag_blue",
      "deeperdarker:blue_sculk_transmitter",
      "farmersdelight:blue_canvas_sign",
      "farmersdelight:blue_hanging_canvas_sign",
      "soulcandles:blue_soul_candle"
    ]
  }
}
