{
  "priority": 50,
  "style": "clarity_tooltips:willow",
  "filter": {
    "type": "obscure_tooltips:item",
    "values": [
      "biomesoplenty:willow_log",
      "biomesoplenty:willow_wood",
      "biomesoplenty:stripped_willow_log",
      "biomesoplenty:stripped_willow_wood",
      "biomesoplenty:willow_planks",
      "biomesoplenty:willow_stairs",
      "biomesoplenty:willow_slab",
      "biomesoplenty:willow_fence",
      "biomesoplenty:willow_fence_gate",
      "biomesoplenty:willow_door",
      "biomesoplenty:willow_trapdoor",
      "biomesoplenty:willow_pressure_plate",
      "biomesoplenty:willow_button",
      "biomesoplenty:willow_sign",
      "biomesoplenty:willow_hanging_sign",
      "biomesoplenty:willow_chest_boat",
      "biomesoplenty:willow_boat",
      "wilderwild:willow_log",
      "wilderwild:willow_wood",
      "wilderwild:stripped_willow_log",
      "wilderwild:stripped_willow_wood",
      "wilderwild:hollowed_willow_log",
      "wilderwild:stripped_hollowed_willow_log",
      "wilderwild:willow_planks",
      "wilderwild:willow_stairs",
      "wilderwild:willow_slab",
      "wilderwild:willow_fence",
      "wilderwild:willow_fence_gate",
      "wilderwild:willow_door",
      "wilderwild:willow_trapdoor",
      "wilderwild:willow_pressure_plate",
      "wilderwild:willow_button",
      "wilderwild:willow_sign",
      "wilderwild:willow_hanging_sign",
      "wilderwild:willow_chest_boat",
      "wilderwild:willow_boat"
    ]
  }
}